setup.cfg
setup.py
fuzzy_utils/__init__.py
fuzzy_utils/fuzzy_utils.py
fuzzy_utils.egg-info/PKG-INFO
fuzzy_utils.egg-info/SOURCES.txt
fuzzy_utils.egg-info/dependency_links.txt
fuzzy_utils.egg-info/requires.txt
fuzzy_utils.egg-info/top_level.txt