Metadata-Version: 1.1
Name: fuzzy-utils
Version: 1.6
Summary: Additional fuzzy classes for Factory boy
Home-page: https://github.com/marcoacierno/factoryboy-fuzzyutils
Author: Marco Acierno
Author-email: marcoaciernoemail@gmail.com
License: MIT
Keywords: factory_boy,fuzzy,utils
Platform: UNKNOWN
Classifier: Development Status :: 5 - Production/Stable
Classifier: Intended Audience :: Developers
Classifier: License :: OSI Approved :: MIT License
Classifier: Topic :: Software Development :: Libraries :: Python Modules
Classifier: Topic :: Software Development :: Testing
Classifier: Topic :: Software Development :: Libraries :: Python Modules
Classifier: Operating System :: OS Independent
Classifier: Programming Language :: Python :: 2.7
Classifier: Programming Language :: Python :: 3
Classifier: Programming Language :: Python :: 3.2
Classifier: Programming Language :: Python :: 3.3
Classifier: Programming Language :: Python :: 3.4
Classifier: Programming Language :: Python :: 3.5
